buildingblocks/__init__.py
buildingblocks/bb.py
buildingblocks-0.0.15.dist-info/LICENSE.txt
buildingblocks-0.0.15.dist-info/METADATA
buildingblocks-0.0.15.dist-info/WHEEL
buildingblocks-0.0.15.dist-info/top_level.txt
buildingblocks-0.0.15.dist-info/RECORD
