Metadata-Version: 2.1
Name: buildingblocks
Version: 0.0.15
Summary: Some Mathematical Tools for Data Curation and Analysis
Home-page: https://github.com/naraharisetti/BuildingBlocksExamples
Author: Pavan Kumar Naraharisetti
Author-email: naraharisetti@gmail.com
License: UNKNOWN
Platform: UNKNOWN
Classifier: Programming Language :: Python :: 3
Classifier: License :: OSI Approved :: MIT License
Classifier: Operating System :: OS Independent
Requires-Python: >=3.6
License-File: LICENSE.txt
